massgitleaks.py
massgitleaks-25.1.dist-info/licenses/LICENSE
massgitleaks-25.1.dist-info/METADATA
massgitleaks-25.1.dist-info/WHEEL
massgitleaks-25.1.dist-info/entry_points.txt
massgitleaks-25.1.dist-info/top_level.txt
massgitleaks-25.1.dist-info/RECORD
