Metadata-Version: 2.4
Name: massgitleaks
Version: 25.1
Summary: Automate gitleaks scanning across multiple repositories
Author-email: Vizz <vizzdoom@gmail.com>
License-Expression: GPL-3.0
Project-URL: Homepage, https://github.com/vizzdoom/massgitleaks
Project-URL: Bug Reports, https://github.com/vizzdoom/massgitleaks/issues
Project-URL: Source Code, https://github.com/vizzdoom/massgitleaks
Keywords: python,git,cli,security,devops,automation,tools,scanner,secret,secrets,hacking,ci-cd,secops,cybersecurity,pentesting,security-tools,devsecops,gitleaks,secrets-detection
Classifier: Intended Audience :: Developers
Classifier: Intended Audience :: System Administrators
Classifier: Topic :: Security
Classifier: Topic :: Software Development :: Version Control :: Git
Classifier: Programming Language :: Python :: 3
Classifier: Programming Language :: Python :: 3.12
Classifier: Programming Language :: Python :: 3.13
Classifier: Programming Language :: Python :: 3.14
Classifier: Operating System :: OS Independent
Requires-Python: >=3.12
License-File: LICENSE
Requires-Dist: colorama>=0.4.6
Requires-Dist: rich-argparse>=1.7.1
Dynamic: license-file
